{
  "category": "hospital-basics",
  "subCategory": "pre-construction/demolition",
  "itemCount": 1,
  "lastUpdated": "2026-01-21T08:18:50.113Z",
  "items": [
    {
      "id": "notion-2ed62aded336",
      "source": "notion",
      "pageId": "2ed62ade-d336-8185-8bd9-edc7afe92318",
      "question": "🔧 철거 및 운영 필수 설비",
      "answer": "💡 플래너 업무를 하는데 있어서 필수적인 내용만 모아두었어요.\n당장 내일 미팅 나가서 앉아있어도 큰 문제가 안 되는 수준이 목표에요.\n# 병의원 철거 및 운영 필수 설비에 대한 이해\n## 개원 과정에서 철거 및 운영 필수 설비는 무엇을 뜻하나요?\n병원 운영의 바탕이 되는 기본 시설들을 말해요.\n• 철거\n• 냉난방기(에어컨, 히터)\n• 공조·환기(덕트, 환풍 시스템)\n• 소방 설비(스프링클러, 감지기 등)\n(단, ‘기반 설비’ 는 공식적인 용어는 아니에요. \n현장에서는 기계설비(냉난방/공조), 소방설비, 철거 라고 각각 불리어요.)\n## 병의원 개원에서 기반 설비가 왜 중요한가요?\n• 냉난방이 부족하면 환자·직원이 불편해하고 병원 이미지가 나빠질 수 있어요.\n• 환기가 안 되면 냄새·답답함으로 위생 문제와 재방문 저하가 생길 수 있어요.\n• 소방 설비가 기준에 맞지 않으면 준공검사를 통과하지 못해 개원 자체가 지연될 수 있어요.\n##  어떤 게 중요한가요?\n• 냉난방기의 용량과 설치 상태\n• 공조·환기의 위치와 풍량\n• 소방 설비의 설치 여부와 법적 기준 충족\n# 병의원 기반 설비 관련 기초 지식 \n## 절차 및 순서 : 큰 그림 익히기\n외우기 쉽게 이름만 따로 구분해서 확인하면 아래와 같아요.\n```\n실측 → 견적 및 계약 → 작업 → 작업 완료 및 인테리어 착공\n```\n## 플래너님께서 아셔야 할 핵심 개념\n## 1. 철거\n• 전유부 철거 : 내가 임대한 공간 안에서만 철거 가능, 건물 공용 부분은 건드릴 수 없음.\n• 양도·양수 철거 : 기존 병원을 인수받을 땐 현장소장이 정해져야 철거가 가능함.\n• 폐기물 반출 : 철거하면서 나온 쓰레기는 그냥 버리면 안 되고, 규정대로 신고하고 버려야 함.\n💡 신규 플래너 분들을 위한 팁\n[전유부? 공용부?]\n1. 전유부(專有部)\n• 뜻: 내가 임차(계약)해서 단독으로 쓰는 공간.\n• 예: 병원 내부(진료실, 대기실, 데스크, 상담실 등)\n• 포인트: 임차인이 마음대로 인테리어·철거 가능 (건물주 허가 전제).\n2. 공용부(共用部)\n• 뜻: 건물 안에서 여러 세입자가 함께 쓰는 공간.\n• 예: 복도, 계단, 화장실(공용일 경우), 엘리베이터 홀\n• 포인트: 개별 임차인이 임의로 공사·철거 불가, 건물주·관리사무소 승인 필수.\n3. 어떻게 적용될까?\n• 철거/배선 공사: 전유부는 자유롭게 가능하지만, 공용부는 절차 없이는 불법.\n• 소방·배기 설비: 공용부에 연결된 설비는 건물 전체와 관련 → 협의 필수.\n• 양도·양수 시: 현장소장이 없으면 철거 자체가 불가능한 이유도, 공용부 규정과 맞물려 있기 때문.\n## 2. 공조덕트\n• 브랜치 덕트 : 큰 환기 통로에서 갈라져 나와 진료실·화장실 같은 데 공기를 넣어주는 작은 길.\n• 댐퍼 : 덕트 안에 달린 ‘문’ 같은 것, 열면 공기 통하고 닫으면 차단됨.\n• 덕트팬(배기팬) : 덕트 안에서 바람을 세게 밀어주는 선풍기. 힘이 약하면 냄새가 안 빠짐.\n## 3. 냉난방\n• EHP(히트펌프) : 큰 건물용 에어컨 시스템. 병원 전체를 한 번에 시원하게/따뜻하게 해줌.\n• 드레인 배수 : 에어컨에서 나온 물을 밖으로 빼내는 통로. 막히면 물 새고 곰팡이 남.\n• 실외기 자리 : 실외기를 아무 데나 못 놓는 경우가 있어서, 위치를 미리 정해야 함.\n## 4. 소방\n• 소방 존(Zone) : 소방 장비가 묶여 있는 구역 단위. 한 구역에 문제 있으면 전체 허가가 안 남.\n• 사이드월 헤드 : 벽에서 물 뿌려주는 스프링클러. 인테리어 디자인과 부딪힐 수 있음.\n• 화재 수신반 : 건물 전체 소방 장치를 한곳에서 관리하는 판넬. 병원 공사할 땐 꼭 연결 확인 필요.\n## 절차별 세부 설명\n### 1. 실측 \n• 시기: 잔금일 전까지\n• 왜 하는 걸까?\n• 실제 현장의 구조와 도면(평면도)이 다른 경우가 많기 때문에, 정확한 치수를 다시 확인하기 위해\n• 전기·배선·소방 등 기반 설비 상태를 직접 확인해야 이후 설계에 반영 가능하기 때문이에요.\n💡 신규 플래너 분들을 위한 팁\n원장님께 소개시켜드릴 기반 설비 업체에게 다음과 같은 사항을 안내해주면 좋아요.\n1. 소재지 정보\n1. 현장 상황\n1. 실측 가능 일시\n### 2. 견적 및 계약 \n▸ 견적서 및 계약서 목록\n\n• 어떻게 진행될까? : 인테리어 업체 측에서 모든 기반 설비 업체의 견적서와 계약서를 배포해요 \n▸ 견적 및 계약이 이뤄지는 카톡\n\n### 3. 작업 & 4. 작료\n• 시기: 잔금일 당일부터 철거-냉난방/공조덕트-소방 순으로 1주일 정도\n# 플래너의 역할\n## 기반 설비 영역에서 자주 발생하는 문제들\n### 1. 실측 시간 확보 어려움\n소음이 많이 발생하는 공사라 건물주·관리사무소 협의가 필요해요. \n게다가 양도인 사정을 고려해야하는 경우도 있어요. \n### 2. 견적 분석 어려움\n견적서에 나온 방식·용어가 낯설어서 금액 차이가 왜 나는지 이해가 안 됨.\n예시) “어떤 업체는 ‘덕트 신설’이라고 쓰고, 다른 업체는 ‘덕트 보강’이라고만 써요.”\n### 3. 공정 완성도 평가의 어려움 \n시운전(가동 테스트) 때는 잘 된 것 같아도 실제로는 성능이 부족하거나 누락된 경우가 많음.\n예시) “에어컨은 켜지는데 풍량이 약해서 대기실 끝까지 바람이 안 가요.”\n### 플래너님께서 해주셔야 하는 일 \n결국, 플래너님은 문제 해결사가 되어야 해요. \n다시 말해, 인테리어 과정 중에 발생하는 모든 문제 해결하기 위해 최선을 다 해야 해요.\n### 1. 일정 조율\n건물주·관리실·업체와 소통해 실측·시공이 가능한 시간을 확보해요.\n💡 신규 플래너 분들을 위한 팁\nhttps://docs.google.com/spreadsheets/d/1DQDshVkt9j4zgf4jnTZUAaZfKV2O5gPHpJ6VzqM8KsA/edit?ouid=115032068196208799013&usp=sheets_home&ths=true 를 통해 확인해두면 좋아요.\n### 2. 견적 책정 방식 설명\n원장님이 이해할 수 있도록 “이 금액은 자재, 이 금액은 인건비”처럼 항목을 풀어서 설명\n업체마다 용어가 달라 생기는 혼란을 통일해서 전달해드려요.\n### 3. 공정 완성도 평가 지원\n냉난방기, 덕트, 소방, 급배기 같은 설비가 실제로 작동하는지 현장에서 확인해요\n문제가 있으면 바로 업체에 피드백 → 재작업 유도",
      "metadata": {
        "field": "플래너 AI",
        "topic": "철거 및 운영 필수 설비",
        "category": "페이지",
        "icon": "🔧",
        "lastUpdated": "2026-01-19T05:28:00.000Z",
        "parentType": "block_id",
        "structuredCategory": "hospital-basics",
        "structuredSubCategory": "pre-construction/demolition"
      }
    }
  ]
}